{
    "clean_data": "Job Id 745721 Experience 2 to 14 Years Qualifications MCA Salary Range $59K$88K location Beijing Country China latitude 358617 longitude 1041954 Work Type FullTime Company Size 18017 Job Posting Date 20220324 Preference Both Contact Person Patricia Medina Contact 001 Job Title Speech Therapist Role Pediatric Speech Therapist Job Portal FlexJobs Job Description Pediatric Speech Therapists provide speech therapy to children with speech and language disorders They assess and treat communication difficulties to improve language skills Benefits Legal Assistance Bonuses and Incentive Programs Wellness Programs Employee Discounts Retirement Plans skills Pediatric speech therapy Speechlanguage assessment Individualized treatment plans Child development Communication skills Responsibilities Assess and treat speech and language disorders in children Provide therapy for articulation language development and communication skills Collaborate with parents and educators Company Hartford Financial Services Group Company Profile SectorFinancial ServicesIndustryInsurance Property and Casualty Stock)CityHartfordStateConnecticutZip6155Website J Swift",
    "entities": [
        "Work Type FullTime Company Size",
        "China",
        "Company Hartford Financial Services Group Company Profile SectorFinancial ServicesIndustryInsurance Property and Casualty",
        "Child development Communication",
        "Individualized",
        "Beijing"
    ],
    "extracted_keywords": [
        "Job",
        "I",
        "d",
        "Experience",
        "Years",
        "Qualifications",
        "MCA",
        "Salary",
        "Range",
        "K",
        "location",
        "Beijing",
        "Country",
        "China",
        "latitude",
        "Work",
        "Type",
        "FullTime",
        "Company",
        "Size",
        "Job",
        "Posting",
        "Date",
        "Preference",
        "Contact",
        "Person",
        "Patricia",
        "Medina",
        "Contact",
        "Job",
        "Title",
        "Speech",
        "Therapist",
        "Role",
        "Pediatric",
        "Speech",
        "Therapist",
        "Job",
        "Portal",
        "FlexJobs",
        "Job",
        "Description",
        "Pediatric",
        "Speech",
        "Therapists",
        "speech",
        "therapy",
        "children",
        "speech",
        "language",
        "disorders",
        "communication",
        "difficulties",
        "language",
        "skills",
        "Legal",
        "Assistance",
        "Bonuses",
        "Incentive",
        "Programs",
        "Wellness",
        "Programs",
        "Employee",
        "Discounts",
        "Retirement",
        "Plans",
        "speech",
        "therapy",
        "Speechlanguage",
        "assessment",
        "treatment",
        "Child",
        "development",
        "Communication",
        "skills",
        "Responsibilities",
        "speech",
        "language",
        "disorders",
        "children",
        "therapy",
        "articulation",
        "language",
        "development",
        "communication",
        "skills",
        "Collaborate",
        "parents",
        "educators",
        "Company",
        "Hartford",
        "Financial",
        "Services",
        "Group",
        "Company",
        "Profile",
        "SectorFinancial",
        "ServicesIndustryInsurance",
        "Property",
        "Casualty",
        "Stock)CityHartfordStateConnecticutZip6155Website",
        "J",
        "Swift"
    ],
    "job_desc_data": "{'Job Id': '2519939608745721', 'Experience': '2 to 14 Years', 'Qualifications': 'MCA', 'Salary Range': '$59K-$88K', 'location': 'Beijing', 'Country': 'China', 'latitude': '35.8617', 'longitude': '104.1954', 'Work Type': 'Full-Time', 'Company Size': '18017', 'Job Posting Date': '2022-03-24', 'Preference': 'Both', 'Contact Person': 'Patricia Medina', 'Contact': '001-372-599-4126', 'Job Title': 'Speech Therapist', 'Role': 'Pediatric Speech Therapist', 'Job Portal': 'FlexJobs', 'Job Description': 'Pediatric Speech Therapists provide speech therapy to children with speech and language disorders. They assess and treat communication difficulties to improve language skills.', 'Benefits': \"{'Legal Assistance, Bonuses and Incentive Programs, Wellness Programs, Employee Discounts, Retirement Plans'}\", 'skills': 'Pediatric speech therapy Speech-language assessment Individualized treatment plans Child development Communication skills', 'Responsibilities': 'Assess and treat speech and language disorders in children. Provide therapy for articulation, language development, and communication skills. Collaborate with parents and educators.', 'Company': 'Hartford Financial Services Group', 'Company Profile': '{\"Sector\":\"Financial Services\",\"Industry\":\"Insurance: Property and Casualty (Stock)\",\"City\":\"Hartford\",\"State\":\"Connecticut\",\"Zip\":\"6155\",\"Website\":\"www.thehartford.com\",\"Ticker\":\"HIG\",\"CEO\":\"Christopher J. Swift\"}'}",
    "unique_id": "274de766-4ea3-49f9-a6bb-62a2d2c6b784"
}