{
    "clean_data": "Job Id 109893 Experience 3 to 10 Years Qualifications BTech Salary Range $59K-$90K location Kigali Country Rwanda latitude -19403 longitude 298739 Work Type Intern Company Size 118921 Job Posting Date 2022-03-23 Preference Female Contact Person Renee Weaver Contact  Job Title Sales Representative Role Inside Sales Representative Job Portal Jobs2Careers Job Description Inside Sales Representatives are responsible for selling products or services to customers over the phone or through online channels They engage with leads answer customer inquiries and use persuasive communication to close sales and meet revenue targets Benefits Childcare Assistance Paid Time Off PTO Relocation Assistance Flexible Work Arrangements Professional Development skills Sales prospecting and lead generation Sales presentation and communication CRM software eg Salesforce Sales negotiation and closing techniques Product knowledge Relationship building Responsibilities Identify and qualify sales leads conduct sales presentations and close deals through phone and email Maintain accurate sales records and reports Provide excellent customer service throughout the sales process Company Old Republic International Company Profile SectorInsuranceIndustryInsurance Property and Casualty StockCityChicagoStateIllinoisZip60601Website R Smiddy",
    "entities": [
        "Company Old Republic International Company Profile SectorInsuranceIndustryInsurance",
        "Kigali Country Rwanda",
        "Responsibilities Identify",
        "Work Type Intern Company Size"
    ],
    "extracted_keywords": [
        "Job",
        "I",
        "d",
        "Experience",
        "Years",
        "Qualifications",
        "BTech",
        "Salary",
        "Range",
        "K",
        "location",
        "Kigali",
        "Country",
        "Rwanda",
        "latitude",
        "longitude",
        "Work",
        "Type",
        "Intern",
        "Company",
        "Size",
        "Job",
        "Posting",
        "Date",
        "Preference",
        "Female",
        "Contact",
        "Person",
        "Renee",
        "Weaver",
        "Contact",
        "Job",
        "Title",
        "Sales",
        "Representative",
        "Role",
        "Sales",
        "Representative",
        "Job",
        "Portal",
        "Jobs2Careers",
        "Job",
        "Description",
        "Sales",
        "Representatives",
        "products",
        "services",
        "customers",
        "phone",
        "channels",
        "leads",
        "answer",
        "customer",
        "inquiries",
        "communication",
        "sales",
        "revenue",
        "targets",
        "Benefits",
        "Childcare",
        "Assistance",
        "Time",
        "Off",
        "PTO",
        "Relocation",
        "Assistance",
        "Flexible",
        "Work",
        "Arrangements",
        "Professional",
        "Development",
        "Sales",
        "generation",
        "Sales",
        "presentation",
        "communication",
        "CRM",
        "software",
        "eg",
        "Salesforce",
        "Sales",
        "negotiation",
        "closing",
        "techniques",
        "Product",
        "knowledge",
        "Relationship",
        "building",
        "Responsibilities",
        "sales",
        "conduct",
        "sales",
        "presentations",
        "deals",
        "phone",
        "email",
        "sales",
        "records",
        "reports",
        "customer",
        "service",
        "sales",
        "process",
        "Company",
        "Old",
        "Republic",
        "International",
        "Company",
        "Profile",
        "Property",
        "Casualty",
        "StockCityChicagoStateIllinoisZip60601Website",
        "R",
        "Smiddy"
    ],
    "job_desc_data": "{'Job Id': '2485433532109893', 'Experience': '3 to 10 Years', 'Qualifications': 'B.Tech', 'Salary Range': '$59K-$90K', 'location': 'Kigali', 'Country': 'Rwanda', 'latitude': '-1.9403', 'longitude': '29.8739', 'Work Type': 'Intern', 'Company Size': '118921', 'Job Posting Date': '2022-03-23', 'Preference': 'Female', 'Contact Person': 'Renee Weaver', 'Contact': '307-565-9584', 'Job Title': 'Sales Representative', 'Role': 'Inside Sales Representative', 'Job Portal': 'Jobs2Careers', 'Job Description': 'Inside Sales Representatives are responsible for selling products or services to customers over the phone or through online channels. They engage with leads, answer customer inquiries, and use persuasive communication to close sales and meet revenue targets.', 'Benefits': \"{'Childcare Assistance, Paid Time Off (PTO), Relocation Assistance, Flexible Work Arrangements, Professional Development'}\", 'skills': 'Sales prospecting and lead generation Sales presentation and communication CRM software (e.g., Salesforce) Sales negotiation and closing techniques Product knowledge Relationship building', 'Responsibilities': 'Identify and qualify sales leads, conduct sales presentations, and close deals through phone and email. Maintain accurate sales records and reports. Provide excellent customer service throughout the sales process.', 'Company': 'Old Republic International', 'Company Profile': '{\"Sector\":\"Insurance\",\"Industry\":\"Insurance: Property and Casualty (Stock)\",\"City\":\"Chicago\",\"State\":\"Illinois\",\"Zip\":\"60601\",\"Website\":\"www.oldrepublic.com\",\"Ticker\":\"ORI\",\"CEO\":\"Craig R. Smiddy\"}'}",
    "unique_id": "759325c6-202e-49fe-908c-a7ea3659b6ca"
}