{
    "clean_data": "Job Id 99487 Experience 1 to 11 Years Qualifications MCom Salary Range $62K$117K location Oslo Country Norway latitude 60472 longitude 84689 Work Type Intern Company Size 40002 Job Posting Date 20220421 Preference Female Contact Person Christy Ramos Contact x71661 Job Title Business Analyst Role Data Business Analyst Job Portal USAJOBS Job Description Data Business Analysts focus on datarelated projects They collect and analyze data identify trends and provide insights to support datadriven decisionmaking within the organization Benefits Flexible Spending Accounts FSAs Relocation Assistance Legal Assistance Employee Recognition Programs Financial Counseling skills Data analysis Data modeling Data visualization SQL Data tools eg Tableau Responsibilities Focus on data analysis data modeling and data visualization to support business decisionmaking Develop and maintain data dictionaries and metadata Collaborate with data engineers and analysts Company Owens & Minor Company Profile SectorHealthcare ServicesIndustryWholesalers Health CareCityMechanicsvilleStateVirginiaZip23116Website A Pesicka",
    "entities": [
        "Develop",
        "SQL Data",
        "Company Owens & Minor Company Profile SectorHealthcare ServicesIndustryWholesalers Health CareCityMechanicsvilleStateVirginiaZip23116Website A Pesicka",
        "Tableau Responsibilities Focus"
    ],
    "extracted_keywords": [
        "Job",
        "I",
        "d",
        "Experience",
        "Years",
        "Qualifications",
        "MCom",
        "Salary",
        "Range",
        "K",
        "location",
        "Oslo",
        "Country",
        "Norway",
        "latitude",
        "Work",
        "Type",
        "Intern",
        "Company",
        "Size",
        "Job",
        "Posting",
        "Date",
        "Preference",
        "Female",
        "Contact",
        "Person",
        "Christy",
        "Ramos",
        "Contact",
        "x71661",
        "Job",
        "Title",
        "Business",
        "Analyst",
        "Role",
        "Data",
        "Business",
        "Analyst",
        "Job",
        "Portal",
        "USAJOBS",
        "Job",
        "Description",
        "Data",
        "Business",
        "Analysts",
        "projects",
        "data",
        "trends",
        "insights",
        "organization",
        "Benefits",
        "Flexible",
        "Spending",
        "Accounts",
        "FSAs",
        "Relocation",
        "Assistance",
        "Legal",
        "Assistance",
        "Employee",
        "Recognition",
        "Programs",
        "Financial",
        "Counseling",
        "Data",
        "analysis",
        "Data",
        "Data",
        "visualization",
        "SQL",
        "Data",
        "tools",
        "eg",
        "Tableau",
        "Responsibilities",
        "Focus",
        "data",
        "analysis",
        "data",
        "modeling",
        "data",
        "visualization",
        "business",
        "Develop",
        "data",
        "dictionaries",
        "metadata",
        "Collaborate",
        "data",
        "engineers",
        "analysts",
        "Company",
        "Owens",
        "Minor",
        "Company",
        "Profile",
        "SectorHealthcare",
        "ServicesIndustryWholesalers",
        "Health",
        "CareCityMechanicsvilleStateVirginiaZip23116Website",
        "A",
        "Pesicka"
    ],
    "job_desc_data": "{'Job Id': '530968105499487', 'Experience': '1 to 11 Years', 'Qualifications': 'M.Com', 'Salary Range': '$62K-$117K', 'location': 'Oslo', 'Country': 'Norway', 'latitude': '60.472', 'longitude': '8.4689', 'Work Type': 'Intern', 'Company Size': '40002', 'Job Posting Date': '2022-04-21', 'Preference': 'Female', 'Contact Person': 'Christy Ramos', 'Contact': '929-252-9808x71661', 'Job Title': 'Business Analyst', 'Role': 'Data Business Analyst', 'Job Portal': 'USAJOBS', 'Job Description': 'Data Business Analysts focus on data-related projects. They collect and analyze data, identify trends, and provide insights to support data-driven decision-making within the organization.', 'Benefits': \"{'Flexible Spending Accounts (FSAs), Relocation Assistance, Legal Assistance, Employee Recognition Programs, Financial Counseling'}\", 'skills': 'Data analysis Data modeling Data visualization SQL Data tools (e.g., Tableau)', 'Responsibilities': 'Focus on data analysis, data modeling, and data visualization to support business decision-making. Develop and maintain data dictionaries and metadata. Collaborate with data engineers and analysts.', 'Company': 'Owens & Minor', 'Company Profile': '{\"Sector\":\"Healthcare Services\",\"Industry\":\"Wholesalers: Health Care\",\"City\":\"Mechanicsville\",\"State\":\"Virginia\",\"Zip\":\"23116\",\"Website\":\"www.owens-minor.com\",\"Ticker\":\"OMI\",\"CEO\":\"Edward A. Pesicka\"}'}",
    "unique_id": "c478c63c-710b-4a50-b6bf-23397f29c399"
}