{
    "clean_data": "Job Id 27961 Experience 0 to 10 Years Qualifications MBA Salary Range $63K$85K location Manila Country Philippines latitude 12879721 longitude 121774017 Work Type Contract Company Size 21486 Job Posting Date 20230804 Preference Both Contact Person Bryan Bowers Contact x93337 Job Title Network Administrator Role Network Security Analyst Job Portal USAJOBS Job Description Protect an organizations computer networks and systems from security threats monitor network traffic and respond to incidents Benefits Employee Assistance Programs EAP Tuition Reimbursement ProfitSharing Transportation Benefits Parental Leave skills Network security protocols Intrusion detection and prevention Security incident response Firewall administration Vulnerability assessment Security policies and procedures Log analysis Ethical hacking Problemsolving Communication skills Attention to detail Responsibilities Manage and secure computer networks including firewalls and intrusion detection systems Monitor network traffic for security threats Implement security policies and procedures Company Jabil Company Profile SectorManufacturingIndustrySemiconductors and Other Electronic ComponentsCitySt PetersburgStateFloridaZip33716Website T Mondello",
    "entities": [
        "Company Jabil Company Profile",
        "Manila",
        "Log analysis Ethical hacking Problemsolving Communication",
        "Philippines"
    ],
    "extracted_keywords": [
        "Job",
        "I",
        "d",
        "Experience",
        "Years",
        "Qualifications",
        "MBA",
        "Salary",
        "Range",
        "K",
        "location",
        "Manila",
        "Country",
        "Philippines",
        "latitude",
        "Work",
        "Type",
        "Contract",
        "Company",
        "Size",
        "Job",
        "Posting",
        "Date",
        "Preference",
        "Contact",
        "Person",
        "Bryan",
        "Bowers",
        "Contact",
        "x93337",
        "Job",
        "Title",
        "Network",
        "Administrator",
        "Role",
        "Network",
        "Security",
        "Analyst",
        "Job",
        "Portal",
        "USAJOBS",
        "Job",
        "Description",
        "organizations",
        "computer",
        "networks",
        "systems",
        "security",
        "threats",
        "network",
        "traffic",
        "incidents",
        "Benefits",
        "Employee",
        "Assistance",
        "Programs",
        "EAP",
        "Tuition",
        "Reimbursement",
        "ProfitSharing",
        "Transportation",
        "Benefits",
        "Parental",
        "Leave",
        "Network",
        "security",
        "protocols",
        "Intrusion",
        "detection",
        "prevention",
        "Security",
        "incident",
        "response",
        "Firewall",
        "administration",
        "Vulnerability",
        "assessment",
        "Security",
        "policies",
        "procedures",
        "analysis",
        "hacking",
        "Problemsolving",
        "Communication",
        "Attention",
        "Responsibilities",
        "computer",
        "networks",
        "firewalls",
        "intrusion",
        "detection",
        "systems",
        "Monitor",
        "network",
        "traffic",
        "security",
        "threats",
        "security",
        "policies",
        "procedures",
        "Company",
        "Jabil",
        "Company",
        "Profile",
        "SectorManufacturingIndustrySemiconductors",
        "ComponentsCitySt",
        "PetersburgStateFloridaZip33716Website",
        "T",
        "Mondello"
    ],
    "job_desc_data": "{'Job Id': '863631623027961', 'Experience': '0 to 10 Years', 'Qualifications': 'MBA', 'Salary Range': '$63K-$85K', 'location': 'Manila', 'Country': 'Philippines', 'latitude': '12.879721', 'longitude': '121.774017', 'Work Type': 'Contract', 'Company Size': '21486', 'Job Posting Date': '2023-08-04', 'Preference': 'Both', 'Contact Person': 'Bryan Bowers', 'Contact': '(900)892-8226x93337', 'Job Title': 'Network Administrator', 'Role': 'Network Security Analyst', 'Job Portal': 'USAJOBS', 'Job Description': 'Protect an organizations computer networks and systems from security threats, monitor network traffic, and respond to incidents.', 'Benefits': \"{'Employee Assistance Programs (EAP), Tuition Reimbursement, Profit-Sharing, Transportation Benefits, Parental Leave'}\", 'skills': 'Network security protocols Intrusion detection and prevention Security incident response Firewall administration Vulnerability assessment Security policies and procedures Log analysis Ethical hacking Problem-solving Communication skills Attention to detail', 'Responsibilities': 'Manage and secure computer networks, including firewalls and intrusion detection systems. Monitor network traffic for security threats. Implement security policies and procedures.', 'Company': 'Jabil', 'Company Profile': '{\"Sector\":\"Manufacturing\",\"Industry\":\"Semiconductors and Other Electronic Components\",\"City\":\"St. Petersburg\",\"State\":\"Florida\",\"Zip\":\"33716\",\"Website\":\"www.jabil.com\",\"Ticker\":\"JBL\",\"CEO\":\"Mark T. Mondello\"}'}",
    "unique_id": "155b0029-06e7-497b-a173-b76197f8e74d"
}