{
    "clean_data": "Job Id 770676 Experience 3 to 14 Years Qualifications BCA Salary Range $56K$91K location Gitega Country Burundi latitude 33731 longitude 299189 Work Type PartTime Company Size 65906 Job Posting Date 20211205 Preference Both Contact Person Megan Martinez Contact 001x2864 Job Title Event Planner Role Event Coordinator Job Portal Snagajob Job Description Event Coordinators plan and execute various events including conferences parties and meetings managing logistics budgets and vendor relationships Benefits Childcare Assistance Paid Time Off PTO Relocation Assistance Flexible Work Arrangements Professional Development skills Event planning Vendor coordination Budget management Marketing and promotion Logistics Responsibilities Plan and coordinate events including logistics vendor management and timelines Communicate with clients to understand event goals and preferences Ensure smooth event execution Company Bosch Group Company Profile SectorManufacturingIndustryIndustrial ManufacturingCityStuttgartStateN/AZipN/AWebsite Denner",
    "entities": [
        "Company Bosch Group Company",
        "Communicate"
    ],
    "extracted_keywords": [
        "Job",
        "I",
        "d",
        "Experience",
        "Years",
        "Qualifications",
        "BCA",
        "Salary",
        "Range",
        "K",
        "location",
        "Gitega",
        "Country",
        "Burundi",
        "latitude",
        "longitude",
        "Work",
        "Type",
        "PartTime",
        "Company",
        "Size",
        "Job",
        "Posting",
        "Date",
        "Preference",
        "Contact",
        "Person",
        "Megan",
        "Martinez",
        "Contact",
        "Job",
        "Title",
        "Event",
        "Planner",
        "Role",
        "Event",
        "Coordinator",
        "Job",
        "Portal",
        "Snagajob",
        "Job",
        "Description",
        "Event",
        "Coordinators",
        "events",
        "conferences",
        "parties",
        "meetings",
        "logistics",
        "budgets",
        "vendor",
        "relationships",
        "Benefits",
        "Childcare",
        "Assistance",
        "Time",
        "Off",
        "PTO",
        "Relocation",
        "Assistance",
        "Flexible",
        "Work",
        "Arrangements",
        "Professional",
        "Development",
        "skills",
        "Event",
        "Vendor",
        "coordination",
        "Budget",
        "management",
        "Marketing",
        "promotion",
        "Logistics",
        "Responsibilities",
        "Plan",
        "events",
        "logistics",
        "vendor",
        "management",
        "timelines",
        "Communicate",
        "clients",
        "event",
        "goals",
        "preferences",
        "event",
        "execution",
        "Company",
        "Bosch",
        "Group",
        "Company",
        "Profile",
        "ManufacturingCityStuttgartStateN",
        "AZipN",
        "AWebsite",
        "Denner"
    ],
    "job_desc_data": "{'Job Id': '2838358509770676', 'Experience': '3 to 14 Years', 'Qualifications': 'BCA', 'Salary Range': '$56K-$91K', 'location': 'Gitega', 'Country': 'Burundi', 'latitude': '-3.3731', 'longitude': '29.9189', 'Work Type': 'Part-Time', 'Company Size': '65906', 'Job Posting Date': '2021-12-05', 'Preference': 'Both', 'Contact Person': 'Megan Martinez', 'Contact': '001-564-292-6586x2864', 'Job Title': 'Event Planner', 'Role': 'Event Coordinator', 'Job Portal': 'Snagajob', 'Job Description': 'Event Coordinators plan and execute various events, including conferences, parties, and meetings, managing logistics, budgets, and vendor relationships.', 'Benefits': \"{'Childcare Assistance, Paid Time Off (PTO), Relocation Assistance, Flexible Work Arrangements, Professional Development'}\", 'skills': 'Event planning Vendor coordination Budget management Marketing and promotion Logistics', 'Responsibilities': 'Plan and coordinate events, including logistics, vendor management, and timelines. Communicate with clients to understand event goals and preferences. Ensure smooth event execution.', 'Company': 'Bosch Group', 'Company Profile': '{\"Sector\":\"Manufacturing\",\"Industry\":\"Industrial Manufacturing\",\"City\":\"Stuttgart\",\"State\":\"N/A\",\"Zip\":\"N/A\",\"Website\":\"www.bosch.com\",\"Ticker\":\"N/A\",\"CEO\":\"Volkmar Denner\"}'}",
    "unique_id": "2a788072-81eb-4bce-ae7b-f9c44291559f"
}