{
    "clean_data": "Job Id 390085 Experience 0 to 15 Years Qualifications MCom Salary Range $64K$115K location Majuro Country Marshall Islands latitude 71315 longitude 1711845 Work Type FullTime Company Size 132105 Job Posting Date 20220921 Preference Both Contact Person John Morris Contact x5675 Job Title Social Media Coordinator Role Content Creator Job Portal FlexJobs Job Description Create engaging and relevant content such as articles videos or social media posts to promote brands or products Benefits Legal Assistance Bonuses and Incentive Programs Wellness Programs Employee Discounts Retirement Plans skills Content creation eg writing editing graphic design video production Content marketing Social media management SEO optimization Creative storytelling Audience engagement Analytics and reporting Adaptability Communication skills Creativity Responsibilities Create compelling and shareable content for social media platforms including text images and videos Collaborate with designers and photographers for visuals Engage with the audience and respond to comments Company Dr Reddys Laboratories Company Profile SectorPharmaceuticalsIndustryPharmaceuticalsCityHyderabadStateTelanganaZip500038Website Israeli",
    "entities": [
        "Company Dr Reddys Laboratories Company Profile",
        "Adaptability Communication",
        "Majuro Country Marshall Islands"
    ],
    "extracted_keywords": [
        "Job",
        "I",
        "d",
        "Experience",
        "Years",
        "Qualifications",
        "MCom",
        "Salary",
        "Range",
        "K",
        "location",
        "Majuro",
        "Country",
        "Marshall",
        "Islands",
        "latitude",
        "Work",
        "Type",
        "FullTime",
        "Company",
        "Size",
        "Job",
        "Posting",
        "Date",
        "Preference",
        "Contact",
        "Person",
        "John",
        "Morris",
        "Contact",
        "x5675",
        "Job",
        "Title",
        "Social",
        "Media",
        "Coordinator",
        "Role",
        "Content",
        "Creator",
        "Job",
        "Portal",
        "FlexJobs",
        "Job",
        "Description",
        "content",
        "articles",
        "videos",
        "media",
        "posts",
        "brands",
        "products",
        "Benefits",
        "Legal",
        "Assistance",
        "Bonuses",
        "Incentive",
        "Programs",
        "Wellness",
        "Programs",
        "Employee",
        "Discounts",
        "Retirement",
        "Plans",
        "Content",
        "creation",
        "eg",
        "writing",
        "design",
        "video",
        "production",
        "Content",
        "marketing",
        "media",
        "management",
        "SEO",
        "optimization",
        "Audience",
        "engagement",
        "Analytics",
        "Adaptability",
        "Communication",
        "Creativity",
        "Responsibilities",
        "content",
        "media",
        "platforms",
        "text",
        "images",
        "videos",
        "designers",
        "photographers",
        "visuals",
        "Engage",
        "audience",
        "comments",
        "Company",
        "Dr",
        "Reddys",
        "Laboratories",
        "Company",
        "Profile",
        "Israeli"
    ],
    "job_desc_data": "{'Job Id': '1575309707390085', 'Experience': '0 to 15 Years', 'Qualifications': 'M.Com', 'Salary Range': '$64K-$115K', 'location': 'Majuro', 'Country': 'Marshall Islands', 'latitude': '7.1315', 'longitude': '171.1845', 'Work Type': 'Full-Time', 'Company Size': '132105', 'Job Posting Date': '2022-09-21', 'Preference': 'Both', 'Contact Person': 'John Morris', 'Contact': '420.523.4326x5675', 'Job Title': 'Social Media Coordinator', 'Role': 'Content Creator', 'Job Portal': 'FlexJobs', 'Job Description': 'Create engaging and relevant content, such as articles, videos, or social media posts, to promote brands or products.', 'Benefits': \"{'Legal Assistance, Bonuses and Incentive Programs, Wellness Programs, Employee Discounts, Retirement Plans'}\", 'skills': 'Content creation (e.g., writing, editing, graphic design, video production) Content marketing Social media management SEO optimization Creative storytelling Audience engagement Analytics and reporting Adaptability Communication skills Creativity', 'Responsibilities': 'Create compelling and shareable content for social media platforms, including text, images, and videos. Collaborate with designers and photographers for visuals. Engage with the audience and respond to comments.', 'Company': \"Dr. Reddy's Laboratories\", 'Company Profile': '{\"Sector\":\"Pharmaceuticals\",\"Industry\":\"Pharmaceuticals\",\"City\":\"Hyderabad\",\"State\":\"Telangana\",\"Zip\":\"500038\",\"Website\":\"https://www.drreddys.com/\",\"Ticker\":\"DRREDDY\",\"CEO\":\"Erez Israeli\"}'}",
    "unique_id": "b88a1a2d-607a-4a80-ba3f-c218ad064860"
}