{
    "clean_data": "Job Id 96821 Experience 5 to 13 Years Qualifications BBA Salary Range $65K$101K location Accra Country Ghana latitude 79465 longitude 10232 Work Type FullTime Company Size 61416 Job Posting Date 20220802 Preference Female Contact Person Tara Bennett Contact  Job Title IT Administrator Role System Administrator Job Portal FlexJobs Job Description System Administrators manage and maintain computer systems and networks They handle software installations security measures and troubleshooting to ensure system reliability Benefits Flexible Spending Accounts FSAs Relocation Assistance Legal Assistance Employee Recognition Programs Financial Counseling skills System administration Network administration Troubleshooting Security management Server maintenance Backup and recovery Responsibilities Manage and maintain computer systems and servers Install and configure software and hardware Monitor system performance and security Company Scottish Mortgage Investment Trust Company Profile SectorFinancial ServicesIndustryFinancial Services  InvestmentCityEdinburghStateN/AZipN/AWebsite Slater",
    "entities": [
        "Work Type FullTime Company Size",
        "InvestmentCityEdinburghStateN/AZipN/AWebsite Slater",
        "Server",
        "Troubleshooting Security",
        "Company Scottish Mortgage Investment Trust Company Profile SectorFinancial ServicesIndustryFinancial Services"
    ],
    "extracted_keywords": [
        "Job",
        "I",
        "d",
        "Experience",
        "Years",
        "Qualifications",
        "BBA",
        "Salary",
        "Range",
        "K",
        "location",
        "Accra",
        "Country",
        "Ghana",
        "latitude",
        "longitude",
        "Work",
        "Type",
        "FullTime",
        "Company",
        "Size",
        "Job",
        "Posting",
        "Date",
        "Preference",
        "Female",
        "Contact",
        "Person",
        "Tara",
        "Bennett",
        "Contact",
        "Job",
        "Title",
        "IT",
        "Administrator",
        "Role",
        "System",
        "Administrator",
        "Job",
        "Portal",
        "FlexJobs",
        "Job",
        "Description",
        "System",
        "Administrators",
        "computer",
        "systems",
        "networks",
        "software",
        "installations",
        "security",
        "measures",
        "troubleshooting",
        "system",
        "reliability",
        "Benefits",
        "Flexible",
        "Spending",
        "Accounts",
        "FSAs",
        "Relocation",
        "Assistance",
        "Legal",
        "Assistance",
        "Employee",
        "Recognition",
        "Programs",
        "Financial",
        "Counseling",
        "System",
        "administration",
        "Network",
        "administration",
        "Troubleshooting",
        "Security",
        "management",
        "Server",
        "maintenance",
        "Backup",
        "recovery",
        "Responsibilities",
        "computer",
        "systems",
        "servers",
        "configure",
        "software",
        "hardware",
        "Monitor",
        "system",
        "performance",
        "security",
        "Company",
        "Scottish",
        "Mortgage",
        "Investment",
        "Trust",
        "Company",
        "Profile",
        "SectorFinancial",
        "ServicesIndustryFinancial",
        "Services",
        "InvestmentCityEdinburghStateN",
        "AZipN",
        "AWebsite",
        "Slater"
    ],
    "job_desc_data": "{'Job Id': '839561957696821', 'Experience': '5 to 13 Years', 'Qualifications': 'BBA', 'Salary Range': '$65K-$101K', 'location': 'Accra', 'Country': 'Ghana', 'latitude': '7.9465', 'longitude': '-1.0232', 'Work Type': 'Full-Time', 'Company Size': '61416', 'Job Posting Date': '2022-08-02', 'Preference': 'Female', 'Contact Person': 'Tara Bennett', 'Contact': '375-713-8100', 'Job Title': 'IT Administrator', 'Role': 'System Administrator', 'Job Portal': 'FlexJobs', 'Job Description': 'System Administrators manage and maintain computer systems and networks. They handle software installations, security measures, and troubleshooting to ensure system reliability.', 'Benefits': \"{'Flexible Spending Accounts (FSAs), Relocation Assistance, Legal Assistance, Employee Recognition Programs, Financial Counseling'}\", 'skills': 'System administration Network administration Troubleshooting Security management Server maintenance Backup and recovery', 'Responsibilities': 'Manage and maintain computer systems and servers. Install and configure software and hardware. Monitor system performance and security.', 'Company': 'Scottish Mortgage Investment Trust', 'Company Profile': '{\"Sector\":\"Financial Services\",\"Industry\":\"Financial Services - Investment\",\"City\":\"Edinburgh\",\"State\":\"N/A\",\"Zip\":\"N/A\",\"Website\":\"www.bailliegifford.com\",\"Ticker\":\"SMT.L\",\"CEO\":\"Tom Slater\"}'}",
    "unique_id": "65fd75a9-5dd1-412e-9a20-18e28de0cfdc"
}