{
    "clean_data": "Job Id 770115 Experience 2 to 9 Years Qualifications BTech Salary Range $65K-$130K location Apia Country Samoa latitude -13759 longitude -1721046 Work Type Temporary Company Size 128876 Job Posting Date 2023-07-29 Preference Male Contact Person Sean Montgomery Contact  Job Title Substance Abuse Counselor Role Recovery Coach Job Portal CareerBuilder Job Description A Recovery Coach offers guidance and support to individuals in addiction recovery aiding in their journey toward sobriety and helping them build a stable and fulfilling life Benefits Life and Disability Insurance Stock Options or Equity Grants Employee Recognition Programs Health Insurance Social and Recreational Activities skills Addiction recovery support Motivational interviewing Relapse prevention strategies Responsibilities Offer ongoing support and guidance to individuals in recovery Assist with relapse prevention strategies and coping skills Foster a supportive and empathetic relationship Company Alumina Limited Company Profile SectorMining and Metals/AluminumIndustryMiningCitySouth BrisbaneStateQLDZip4101Website Ferraro",
    "entities": [
        "Apia Country Samoa",
        "Company Alumina Limited Company Profile SectorMining",
        "Benefits Life and Disability Insurance Stock Options or Equity Grants Employee Recognition Programs Health Insurance Social and Recreational Activities",
        "Work Type Temporary Company Size",
        "Motivational",
        "BTech",
        "Metals"
    ],
    "extracted_keywords": [
        "Job",
        "I",
        "d",
        "Experience",
        "Years",
        "Qualifications",
        "BTech",
        "Salary",
        "Range",
        "K",
        "location",
        "Apia",
        "Country",
        "Samoa",
        "latitude",
        "longitude",
        "Work",
        "Type",
        "Temporary",
        "Company",
        "Size",
        "Job",
        "Posting",
        "Date",
        "Preference",
        "Male",
        "Contact",
        "Person",
        "Sean",
        "Montgomery",
        "Contact",
        "Job",
        "Title",
        "Substance",
        "Abuse",
        "Counselor",
        "Role",
        "Recovery",
        "Coach",
        "Job",
        "Portal",
        "CareerBuilder",
        "Job",
        "Description",
        "A",
        "Recovery",
        "Coach",
        "guidance",
        "support",
        "individuals",
        "addiction",
        "recovery",
        "aiding",
        "journey",
        "sobriety",
        "life",
        "Life",
        "Disability",
        "Insurance",
        "Stock",
        "Options",
        "Equity",
        "Grants",
        "Employee",
        "Recognition",
        "Programs",
        "Health",
        "Insurance",
        "Social",
        "Recreational",
        "Activities",
        "Addiction",
        "recovery",
        "support",
        "Motivational",
        "Relapse",
        "prevention",
        "strategies",
        "Responsibilities",
        "support",
        "guidance",
        "individuals",
        "recovery",
        "Assist",
        "relapse",
        "prevention",
        "strategies",
        "skills",
        "Foster",
        "relationship",
        "Company",
        "Alumina",
        "Limited",
        "Company",
        "Profile",
        "SectorMining",
        "Metals",
        "AluminumIndustryMiningCitySouth",
        "BrisbaneStateQLDZip4101Website",
        "Ferraro"
    ],
    "job_desc_data": "{'Job Id': '2118681397770115', 'Experience': '2 to 9 Years', 'Qualifications': 'B.Tech', 'Salary Range': '$65K-$130K', 'location': 'Apia', 'Country': 'Samoa', 'latitude': '-13.759', 'longitude': '-172.1046', 'Work Type': 'Temporary', 'Company Size': '128876', 'Job Posting Date': '2023-07-29', 'Preference': 'Male', 'Contact Person': 'Sean Montgomery', 'Contact': '5615227410', 'Job Title': 'Substance Abuse Counselor', 'Role': 'Recovery Coach', 'Job Portal': 'CareerBuilder', 'Job Description': 'A Recovery Coach offers guidance and support to individuals in addiction recovery, aiding in their journey toward sobriety and helping them build a stable and fulfilling life.', 'Benefits': \"{'Life and Disability Insurance, Stock Options or Equity Grants, Employee Recognition Programs, Health Insurance, Social and Recreational Activities'}\", 'skills': 'Addiction recovery support Motivational interviewing Relapse prevention strategies', 'Responsibilities': 'Offer ongoing support and guidance to individuals in recovery. Assist with relapse prevention strategies and coping skills. Foster a supportive and empathetic relationship.', 'Company': 'Alumina Limited', 'Company Profile': '{\"Sector\":\"Mining and Metals/Aluminum\",\"Industry\":\"Mining\",\"City\":\"South Brisbane\",\"State\":\"QLD\",\"Zip\":\"4101\",\"Website\":\"https://www.aluminalimited.com/\",\"Ticker\":\"AWC\",\"CEO\":\"Mike Ferraro\"}'}",
    "unique_id": "19a02db5-81ae-41ad-8f5e-583241273d3a"
}