{
    "clean_data": "Job Id 767527 Experience 1 to 15 Years Qualifications BCom Salary Range $58K$100K location Georgetown Country Guyana latitude 48604 longitude 589302 Work Type PartTime Company Size 125164 Job Posting Date 20220708 Preference Both Contact Person Elizabeth Campbell Contact 001x89264 Job Title Database Administrator Role Database Developer Job Portal Idealist Job Description A Database Developer designs develops and maintains databases They create efficient data structures write queries and ensure data security and integrity Benefits Casual Dress Code Social and Recreational Activities Employee Referral Programs Health and Wellness Facilities Life and Disability Insurance skills Database design and development SQL and database querying Data modeling Programming languages eg Java Python Data security and privacy regulations knowledge Responsibilities Design and implement database systems tables and structures Develop and optimize SQL queries and scripts Ensure data security integrity and backup procedures Company Dell Technologies Company Profile SectorTechnologyIndustryComputers Office EquipmentCityRound RockStateTexasZip78682Website S Dell",
    "entities": [
        "S Dell",
        "SQL",
        "Georgetown Country Guyana",
        "Responsibilities Design",
        "Develop",
        "Company Dell Technologies Company Profile SectorTechnologyIndustryComputers"
    ],
    "extracted_keywords": [
        "Job",
        "I",
        "d",
        "Experience",
        "Years",
        "Qualifications",
        "BCom",
        "Salary",
        "Range",
        "K",
        "location",
        "Georgetown",
        "Country",
        "Guyana",
        "latitude",
        "Work",
        "Type",
        "PartTime",
        "Company",
        "Size",
        "Job",
        "Posting",
        "Date",
        "Preference",
        "Contact",
        "Person",
        "Elizabeth",
        "Campbell",
        "Contact",
        "Job",
        "Title",
        "Database",
        "Administrator",
        "Role",
        "Database",
        "Developer",
        "Job",
        "Portal",
        "Idealist",
        "Job",
        "Description",
        "Database",
        "Developer",
        "databases",
        "data",
        "structures",
        "queries",
        "data",
        "security",
        "integrity",
        "Benefits",
        "Casual",
        "Dress",
        "Code",
        "Social",
        "Recreational",
        "Activities",
        "Employee",
        "Referral",
        "Programs",
        "Health",
        "Wellness",
        "Facilities",
        "Life",
        "Disability",
        "Insurance",
        "Database",
        "design",
        "development",
        "SQL",
        "database",
        "Data",
        "Programming",
        "languages",
        "Java",
        "Python",
        "Data",
        "security",
        "privacy",
        "regulations",
        "knowledge",
        "Responsibilities",
        "Design",
        "database",
        "systems",
        "tables",
        "structures",
        "Develop",
        "SQL",
        "queries",
        "Ensure",
        "data",
        "security",
        "integrity",
        "backup",
        "procedures",
        "Company",
        "Dell",
        "Technologies",
        "Company",
        "Profile",
        "Office",
        "EquipmentCityRound",
        "RockStateTexasZip78682Website",
        "S",
        "Dell"
    ],
    "job_desc_data": "{'Job Id': '2680774211767527', 'Experience': '1 to 15 Years', 'Qualifications': 'B.Com', 'Salary Range': '$58K-$100K', 'location': 'Georgetown', 'Country': 'Guyana', 'latitude': '4.8604', 'longitude': '-58.9302', 'Work Type': 'Part-Time', 'Company Size': '125164', 'Job Posting Date': '2022-07-08', 'Preference': 'Both', 'Contact Person': 'Elizabeth Campbell', 'Contact': '001-836-334-5239x89264', 'Job Title': 'Database Administrator', 'Role': 'Database Developer', 'Job Portal': 'Idealist', 'Job Description': 'A Database Developer designs, develops, and maintains databases. They create efficient data structures, write queries, and ensure data security and integrity.', 'Benefits': \"{'Casual Dress Code, Social and Recreational Activities, Employee Referral Programs, Health and Wellness Facilities, Life and Disability Insurance'}\", 'skills': 'Database design and development SQL and database querying Data modeling Programming languages (e.g., Java, Python) Data security and privacy regulations knowledge', 'Responsibilities': 'Design and implement database systems, tables, and structures. Develop and optimize SQL queries and scripts. Ensure data security, integrity, and backup procedures.', 'Company': 'Dell Technologies', 'Company Profile': '{\"Sector\":\"Technology\",\"Industry\":\"Computers, Office Equipment\",\"City\":\"Round Rock\",\"State\":\"Texas\",\"Zip\":\"78682\",\"Website\":\"www.delltechnologies.com\",\"Ticker\":\"DELL\",\"CEO\":\"Michael S. Dell\"}'}",
    "unique_id": "61c36230-b01c-4289-ac3e-5704f27f60ee"
}