{
    "clean_data": "Job Id 560435 Experience 5 to 9 Years Qualifications BA Salary Range $55K$96K location Saint Georges Country Grenada latitude 121165 longitude 61679 Work Type PartTime Company Size 107658 Job Posting Date 20230724 Preference Male Contact Person Scott Golden Contact x50021 Job Title Product Manager Role Agile Product Owner Job Portal Stack Overflow Jobs Job Description Agile Product Owners work closely with development teams in Agile environments They define and prioritize product backlog items communicate the product vision and ensure that the product increments delivered align with customer needs and project objectives Benefits Transportation Benefits Professional Development Bonuses and Incentive Programs ProfitSharing Employee Discounts skills Agile product development Scrum or Kanban frameworks Backlog management User story writing Prioritization techniques Collaboration with development teams Product vision and strategy Responsibilities Act as the product owner in agile development making critical decisions and ensuring product goals are met Maintain and prioritize the product backlog Communicate with stakeholders and development teams Company CSX Company Profile SectorTransportationIndustryRailroadsCityJacksonvilleStateFloridaZip32202Website R Hinrichs",
    "entities": [
        "Incentive Programs ProfitSharing Employee Discounts",
        "Benefits Transportation Benefits Professional Development Bonuses",
        "Company CSX Company",
        "Kanban",
        "Communicate",
        "Agile"
    ],
    "extracted_keywords": [
        "Job",
        "I",
        "d",
        "Experience",
        "Years",
        "Qualifications",
        "BA",
        "Salary",
        "Range",
        "K",
        "location",
        "Saint",
        "Georges",
        "Country",
        "Grenada",
        "latitude",
        "Work",
        "Type",
        "PartTime",
        "Company",
        "Size",
        "Job",
        "Posting",
        "Date",
        "Preference",
        "Male",
        "Contact",
        "Person",
        "Scott",
        "Golden",
        "Contact",
        "x50021",
        "Job",
        "Title",
        "Product",
        "Manager",
        "Role",
        "Agile",
        "Product",
        "Owner",
        "Job",
        "Portal",
        "Stack",
        "Overflow",
        "Jobs",
        "Job",
        "Description",
        "Agile",
        "Product",
        "Owners",
        "development",
        "teams",
        "environments",
        "product",
        "backlog",
        "items",
        "product",
        "vision",
        "product",
        "increments",
        "customer",
        "needs",
        "project",
        "objectives",
        "Benefits",
        "Transportation",
        "Benefits",
        "Professional",
        "Development",
        "Bonuses",
        "Incentive",
        "Programs",
        "ProfitSharing",
        "Employee",
        "Discounts",
        "product",
        "development",
        "Scrum",
        "Kanban",
        "frameworks",
        "Backlog",
        "management",
        "User",
        "story",
        "Prioritization",
        "techniques",
        "Collaboration",
        "development",
        "teams",
        "Product",
        "vision",
        "strategy",
        "Responsibilities",
        "Act",
        "product",
        "owner",
        "development",
        "decisions",
        "product",
        "goals",
        "Maintain",
        "product",
        "backlog",
        "Communicate",
        "stakeholders",
        "development",
        "teams",
        "Company",
        "CSX",
        "Company",
        "Profile",
        "R",
        "Hinrichs"
    ],
    "job_desc_data": "{'Job Id': '2453650465560435', 'Experience': '5 to 9 Years', 'Qualifications': 'BA', 'Salary Range': '$55K-$96K', 'location': \"Saint George's\", 'Country': 'Grenada', 'latitude': '12.1165', 'longitude': '-61.679', 'Work Type': 'Part-Time', 'Company Size': '107658', 'Job Posting Date': '2023-07-24', 'Preference': 'Male', 'Contact Person': 'Scott Golden', 'Contact': '467.231.6252x50021', 'Job Title': 'Product Manager', 'Role': 'Agile Product Owner', 'Job Portal': 'Stack Overflow Jobs', 'Job Description': 'Agile Product Owners work closely with development teams in Agile environments. They define and prioritize product backlog items, communicate the product vision, and ensure that the product increments delivered align with customer needs and project objectives.', 'Benefits': \"{'Transportation Benefits, Professional Development, Bonuses and Incentive Programs, Profit-Sharing, Employee Discounts'}\", 'skills': 'Agile product development Scrum or Kanban frameworks Backlog management User story writing Prioritization techniques Collaboration with development teams Product vision and strategy', 'Responsibilities': 'Act as the product owner in agile development, making critical decisions and ensuring product goals are met. Maintain and prioritize the product backlog. Communicate with stakeholders and development teams.', 'Company': 'CSX', 'Company Profile': '{\"Sector\":\"Transportation\",\"Industry\":\"Railroads\",\"City\":\"Jacksonville\",\"State\":\"Florida\",\"Zip\":\"32202\",\"Website\":\"www.csx.com\",\"Ticker\":\"CSX\",\"CEO\":\"Joseph R. Hinrichs\"}'}",
    "unique_id": "481d065c-af8f-4111-ba66-240407c06654"
}