{
    "clean_data": "Job Id 782157 Experience 0 to 12 Years Qualifications MTech Salary Range $65K$121K location Torshavn Country Faroe Islands latitude 618926 longitude 69118 Work Type Temporary Company Size 83882 Job Posting Date 20230206 Preference Both Contact Person Lauren Campbell Contact x24531 Job Title Graphic Designer Role Print Graphic Designer Job Portal SimplyHired Job Description Print Graphic Designers design graphics and layouts for printed materials such as brochures posters and packaging They use their creativity and design skills to visually communicate messages and information effectively in printed form Benefits Tuition Reimbursement Stock Options or Equity Grants Parental Leave Wellness Programs Childcare Assistance skills Print design software eg Adobe InDesign Illustrator Layout and composition Print production processes Color theory and management Attention to detail Print industry knowledge Responsibilities Design printed materials such as brochures posters and packaging Choose appropriate printing methods and materials Collaborate with print vendors and ensure quality output Company Spirit Airlines Inc Company Profile SectorTransportation/AirlinesIndustryTransportation  AirlinesCityMiramarStateFLZip33025Website M Christie III",
    "entities": [
        "Color",
        "Adobe InDesign Illustrator Layout",
        "Print",
        "Attention",
        "Work Type Temporary Company Size",
        "Responsibilities Design",
        "Tuition Reimbursement Stock Options",
        "Company Spirit Airlines Inc Company Profile SectorTransportation/AirlinesIndustryTransportation"
    ],
    "extracted_keywords": [
        "Job",
        "I",
        "d",
        "Experience",
        "Years",
        "Qualifications",
        "MTech",
        "Salary",
        "Range",
        "K",
        "location",
        "Torshavn",
        "Country",
        "Faroe",
        "Islands",
        "latitude",
        "Work",
        "Type",
        "Temporary",
        "Company",
        "Size",
        "Job",
        "Posting",
        "Date",
        "Preference",
        "Contact",
        "Person",
        "Lauren",
        "Campbell",
        "Contact",
        "x24531",
        "Job",
        "Title",
        "Graphic",
        "Designer",
        "Role",
        "Print",
        "Graphic",
        "Designer",
        "Job",
        "Portal",
        "SimplyHired",
        "Job",
        "Description",
        "Print",
        "Graphic",
        "Designers",
        "design",
        "graphics",
        "layouts",
        "materials",
        "brochures",
        "posters",
        "packaging",
        "creativity",
        "design",
        "skills",
        "messages",
        "information",
        "form",
        "Benefits",
        "Tuition",
        "Reimbursement",
        "Stock",
        "Options",
        "Equity",
        "Grants",
        "Parental",
        "Leave",
        "Wellness",
        "Programs",
        "Childcare",
        "Assistance",
        "skills",
        "Print",
        "design",
        "software",
        "eg",
        "Adobe",
        "InDesign",
        "Illustrator",
        "Layout",
        "composition",
        "Print",
        "production",
        "theory",
        "management",
        "Attention",
        "Print",
        "industry",
        "knowledge",
        "Responsibilities",
        "Design",
        "materials",
        "brochures",
        "posters",
        "printing",
        "methods",
        "materials",
        "Collaborate",
        "print",
        "vendors",
        "quality",
        "output",
        "Company",
        "Spirit",
        "Airlines",
        "Inc",
        "Company",
        "Profile",
        "SectorTransportation",
        "AirlinesIndustryTransportation",
        "AirlinesCityMiramarStateFLZip33025Website",
        "M",
        "Christie",
        "III"
    ],
    "job_desc_data": "{'Job Id': '1668848686782157', 'Experience': '0 to 12 Years', 'Qualifications': 'M.Tech', 'Salary Range': '$65K-$121K', 'location': 'Torshavn', 'Country': 'Faroe Islands', 'latitude': '61.8926', 'longitude': '-6.9118', 'Work Type': 'Temporary', 'Company Size': '83882', 'Job Posting Date': '2023-02-06', 'Preference': 'Both', 'Contact Person': 'Lauren Campbell', 'Contact': '(904)789-7612x24531', 'Job Title': 'Graphic Designer', 'Role': 'Print Graphic Designer', 'Job Portal': 'SimplyHired', 'Job Description': 'Print Graphic Designers design graphics and layouts for printed materials such as brochures, posters, and packaging. They use their creativity and design skills to visually communicate messages and information effectively in printed form.', 'Benefits': \"{'Tuition Reimbursement, Stock Options or Equity Grants, Parental Leave, Wellness Programs, Childcare Assistance'}\", 'skills': 'Print design software (e.g., Adobe InDesign, Illustrator) Layout and composition Print production processes Color theory and management Attention to detail Print industry knowledge', 'Responsibilities': 'Design printed materials such as brochures, posters, and packaging. Choose appropriate printing methods and materials. Collaborate with print vendors and ensure quality output.', 'Company': 'Spirit Airlines, Inc.', 'Company Profile': '{\"Sector\":\"Transportation/Airlines\",\"Industry\":\"Transportation - Airlines\",\"City\":\"Miramar\",\"State\":\"FL\",\"Zip\":\"33025\",\"Website\":\"https://www.spirit.com/\",\"Ticker\":\"SAVE\",\"CEO\":\"Edward M. Christie III\"}'}",
    "unique_id": "b0aade58-09a8-4355-9052-e0d7a4d8971a"
}