{
    "clean_data": "Job Id 321648 Experience 2 to 11 Years Qualifications MBA Salary Range $57K$116K location Andorra la Vella Country Andorra latitude 425063 longitude 15218 Work Type FullTime Company Size 113819 Job Posting Date 20220801 Preference Both Contact Person Michele Boyd Contact  Job Title Legal Assistant Role Paralegal Job Portal Internshipscom Job Description Assist lawyers with legal research document preparation and case management in law firms or legal departments Benefits Flexible Spending Accounts FSAs Relocation Assistance Legal Assistance Employee Recognition Programs Financial Counseling skills Legal research Document drafting Case management Efiling Legal databases eg LexisNexis Client communication Deposition preparation Trial support Ethics and confidentiality Attention to detail Communication skills Legal software proficiency Responsibilities Assist lawyers in legal research document preparation and case management Draft legal documents and pleadings Organize and maintain case files Company Dr Pepper Snapple Group Inc Company Profile SectorBeverageIndustryFood and BeverageCityPlanoStateTXZip75024Website",
    "entities": [
        "Dr Pepper Snapple Group Inc Company Profile SectorBeverageIndustryFood",
        "Attention",
        "LexisNexis Client",
        "Organize",
        "Draft"
    ],
    "extracted_keywords": [
        "Job",
        "I",
        "d",
        "Experience",
        "Years",
        "Qualifications",
        "MBA",
        "Salary",
        "Range",
        "K",
        "location",
        "Andorra",
        "la",
        "Vella",
        "Country",
        "Andorra",
        "latitude",
        "longitude",
        "Work",
        "Type",
        "FullTime",
        "Company",
        "Size",
        "Job",
        "Posting",
        "Date",
        "Preference",
        "Contact",
        "Person",
        "Michele",
        "Boyd",
        "Contact",
        "Job",
        "Title",
        "Legal",
        "Assistant",
        "Role",
        "Paralegal",
        "Job",
        "Portal",
        "Internshipscom",
        "Job",
        "Description",
        "Assist",
        "lawyers",
        "research",
        "document",
        "preparation",
        "case",
        "management",
        "law",
        "firms",
        "departments",
        "Flexible",
        "Spending",
        "Accounts",
        "FSAs",
        "Relocation",
        "Assistance",
        "Legal",
        "Assistance",
        "Employee",
        "Recognition",
        "Programs",
        "Financial",
        "Counseling",
        "research",
        "Document",
        "Case",
        "management",
        "Efiling",
        "Legal",
        "eg",
        "LexisNexis",
        "Client",
        "communication",
        "Deposition",
        "preparation",
        "Trial",
        "support",
        "Ethics",
        "confidentiality",
        "Attention",
        "Communication",
        "software",
        "proficiency",
        "Responsibilities",
        "lawyers",
        "research",
        "document",
        "preparation",
        "case",
        "management",
        "Draft",
        "documents",
        "pleadings",
        "case",
        "files",
        "Company",
        "Dr",
        "Pepper",
        "Snapple",
        "Group",
        "Inc",
        "Company",
        "Profile",
        "SectorBeverageIndustryFood",
        "BeverageCityPlanoStateTXZip75024Website"
    ],
    "job_desc_data": "{'Job Id': '1182756361321648', 'Experience': '2 to 11 Years', 'Qualifications': 'MBA', 'Salary Range': '$57K-$116K', 'location': 'Andorra la Vella', 'Country': 'Andorra', 'latitude': '42.5063', 'longitude': '1.5218', 'Work Type': 'Full-Time', 'Company Size': '113819', 'Job Posting Date': '2022-08-01', 'Preference': 'Both', 'Contact Person': 'Michele Boyd', 'Contact': '652.250.4929', 'Job Title': 'Legal Assistant', 'Role': 'Paralegal', 'Job Portal': 'Internships.com', 'Job Description': 'Assist lawyers with legal research, document preparation, and case management in law firms or legal departments.', 'Benefits': \"{'Flexible Spending Accounts (FSAs), Relocation Assistance, Legal Assistance, Employee Recognition Programs, Financial Counseling'}\", 'skills': 'Legal research Document drafting Case management E-filing Legal databases (e.g., LexisNexis) Client communication Deposition preparation Trial support Ethics and confidentiality Attention to detail Communication skills Legal software proficiency', 'Responsibilities': 'Assist lawyers in legal research, document preparation, and case management. Draft legal documents and pleadings. Organize and maintain case files.', 'Company': 'Dr. Pepper Snapple Group, Inc.', 'Company Profile': '{\"Sector\":\"Beverage\",\"Industry\":\"Food and Beverage\",\"City\":\"Plano\",\"State\":\"TX\",\"Zip\":\"75024\",\"Website\":\"https://www.drpeppersnapplegroup.com/\",\"Ticker\":\"N/A\",\"CEO\":\"N/A\"}'}",
    "unique_id": "b97a083d-47ce-4ffd-8c14-ecccdb75871a"
}